venteto_dfs/__init__.py
venteto_dfs/abstract_models.py
venteto_dfs/admin.py
venteto_dfs/apps.py
venteto_dfs/context_processors.py
venteto_dfs/models.py
venteto_dfs/tests.py
venteto_dfs/urls.py
venteto_dfs/views.py
venteto_dfs/TMP/views.py
venteto_dfs/migrations/0001_initial.py
venteto_dfs/migrations/__init__.py
venteto_dfs/templates/base.dtl
venteto_dfs/templates/base_GUDE.dtl
venteto_dfs/templates/home.dtl
venteto_dfs/templates/accounts/login.dtl
venteto_dfs/templates/accounts/logout.dtl
venteto_dfs/templates/admin/base.html
venteto_dfs/templates/admin/HIDE/base_site.html
venteto_dfs/templates/errors/404.dtl
venteto_dfs/templates_hide/base.dtl
venteto_dfs/templates_hide/home.dtl
venteto_dfs/templates_hide/js_dt_init_generic.dtl
venteto_dfs/templates_hide/nav_global.dtl
venteto_dfs/templates_hide/admin/base.html
venteto_dfs/templates_hide/admin/base_site.html
venteto_dfs/templates_hide/errors/400.dtl
venteto_dfs/templates_hide/errors/403.dtl
venteto_dfs/templates_hide/errors/404.dtl
venteto_dfs/templates_hide/errors/500.dtl
venteto_dfs/templates_hide/tmp/SAMPLE.md
venteto_dfs/templates_hide/tmp/base-OLD.dtl
venteto_dfs/templates_hide/tmp/experiments.dtl
venteto_dfs/templates_hide/tmp/inspect.dtl
venteto_dfs/templates_hide/tmp/profile.dtl
venteto_dfs/templates_hide/tmp/sh_out.txt
venteto_dfs/templates_hide/tmp/base_inc_deprecated/ana_ga4.dtl
venteto_dfs/templates_hide/tmp/base_inc_deprecated/header.dtl
venteto_dfs/templates_hide/tmp/base_inc_deprecated/svg.dtl
venteto_dfs/templates_hide/tmp/base_inc_deprecated/internal_css/1_proto.css
venteto_dfs/templates_hide/tmp/base_inc_deprecated/internal_css/anchors.css
venteto_dfs/templates_hide/tmp/base_inc_deprecated/internal_css/images.css
venteto_dfs/templates_hide/tmp/base_inc_deprecated/internal_css/tables.css
venteto_dfs-0.0.0.dev0.dist-info/METADATA
venteto_dfs-0.0.0.dev0.dist-info/WHEEL
venteto_dfs-0.0.0.dev0.dist-info/RECORD
