Metadata-Version: 2.1
Name: venteto-dfs
Version: 0.0.0.dev0
Summary: This is a test package and is not intended to be used by the public.
Requires-Python: >=3.12
Requires-Dist: django-htmlmin>=0.11.0
Requires-Dist: django-tree-queries>=0.16.1
Requires-Dist: django>=5.0.2
Requires-Dist: uuid6>=2024.1.12
